iso18245_uz/__init__.py
iso18245_uz/data/alipay_list.csv
iso18245_uz/data/alipay_list_translated.csv
iso18245_uz/data/amex_list.csv
iso18245_uz/data/amex_list_translated.csv
iso18245_uz/data/iso18245_official_list.csv
iso18245_uz/data/iso18245_official_list_translated.csv
iso18245_uz/data/iso18245_ranges.csv
iso18245_uz/data/iso18245_ranges_translated.csv
iso18245_uz/data/mastercard_list.csv
iso18245_uz/data/mastercard_list_translated.csv
iso18245_uz/data/private_ranges.csv
iso18245_uz/data/private_ranges_translated.csv
iso18245_uz/data/stripe_list.csv
iso18245_uz/data/stripe_list_translated.csv
iso18245_uz/data/usda_list.csv
iso18245_uz/data/usda_list_translated.csv
iso18245_uz/data/visa_list.csv
iso18245_uz/data/visa_list_translated.csv
iso18245_uz/py.typed
iso18245_uz-1.4.4.dist-info/METADATA
iso18245_uz-1.4.4.dist-info/WHEEL
iso18245_uz-1.4.4.dist-info/licenses/LICENSE
iso18245_uz-1.4.4.dist-info/RECORD
