Metadata-Version: 2.4
Name: iso18245_uz
Version: 1.4.4
Summary: The ISO 18245 Merchant Category Codes database with descriptions translated from English to Russian and Uzbek
License: MIT
License-File: LICENSE
Author: Jerome Leclanche
Author-email: jerome@leclan.ch
Requires-Python: >=3.8,<4.0
Classifier: Development Status :: 5 - Production/Stable
Classifier: Intended Audience :: Developers
Classifier: License :: OSI Approved :: MIT License
Classifier: Programming Language :: Python :: 3
Classifier: Programming Language :: Python :: 3.8
Classifier: Programming Language :: Python :: 3.9
Classifier: Programming Language :: Python :: 3.10
Classifier: Programming Language :: Python :: 3.11
Classifier: Programming Language :: Python :: 3.12
Classifier: Programming Language :: Python :: 3.13
Classifier: Programming Language :: Python :: 3.14
Classifier: Topic :: Office/Business :: Financial
Classifier: Topic :: Office/Business :: Financial :: Accounting
Classifier: Topic :: Software Development :: Libraries :: Python Modules
Requires-Dist: importlib_resources (>=5.4.0,<6.0.0)
Project-URL: Repository, https://github.com/aslon1213/python-iso18245
